accelbyte_py_sdk/api/csm/__init__.py
accelbyte_py_sdk/api/csm/errors.py
accelbyte_py_sdk/api/csm/models/__init__.py
accelbyte_py_sdk/api/csm/models/apimodel_app_item.py
accelbyte_py_sdk/api/csm/models/apimodel_autoscaling_request.py
accelbyte_py_sdk/api/csm/models/apimodel_autoscaling_response.py
accelbyte_py_sdk/api/csm/models/apimodel_bulk_subscribe_item.py
accelbyte_py_sdk/api/csm/models/apimodel_bulk_subscribe_request.py
accelbyte_py_sdk/api/csm/models/apimodel_cpu_request.py
accelbyte_py_sdk/api/csm/models/apimodel_cpu_response.py
accelbyte_py_sdk/api/csm/models/apimodel_create_app_v2_request.py
accelbyte_py_sdk/api/csm/models/apimodel_create_deployment_v2_request.py
accelbyte_py_sdk/api/csm/models/apimodel_create_deployment_v2_response.py
accelbyte_py_sdk/api/csm/models/apimodel_create_no_sql_app_database_request.py
accelbyte_py_sdk/api/csm/models/apimodel_create_no_sql_database_credential_request.py
accelbyte_py_sdk/api/csm/models/apimodel_create_subscription_request.py
accelbyte_py_sdk/api/csm/models/apimodel_create_subscription_response.py
accelbyte_py_sdk/api/csm/models/apimodel_create_topic_request.py
accelbyte_py_sdk/api/csm/models/apimodel_csm_app_limits_response.py
accelbyte_py_sdk/api/csm/models/apimodel_delete_no_sql_resource_response.py
accelbyte_py_sdk/api/csm/models/apimodel_get_app_image_list_v2_data_item.py
accelbyte_py_sdk/api/csm/models/apimodel_get_app_image_list_v2_data_item_image_scan_result.py
accelbyte_py_sdk/api/csm/models/apimodel_get_app_image_list_v2_data_item_image_scan_status.py
accelbyte_py_sdk/api/csm/models/apimodel_get_app_image_list_v2_response.py
accelbyte_py_sdk/api/csm/models/apimodel_get_app_list_v2_request.py
accelbyte_py_sdk/api/csm/models/apimodel_get_app_list_v2_response.py
accelbyte_py_sdk/api/csm/models/apimodel_get_deployment_list_v2_data_item.py
accelbyte_py_sdk/api/csm/models/apimodel_get_deployment_list_v2_request.py
accelbyte_py_sdk/api/csm/models/apimodel_get_deployment_list_v2_response.py
accelbyte_py_sdk_service_csm-0.11.0.dist-info/METADATA
accelbyte_py_sdk_service_csm-0.11.0.dist-info/WHEEL
accelbyte_py_sdk_service_csm-0.11.0.dist-info/top_level.txt
accelbyte_py_sdk_service_csm-0.11.0.dist-info/RECORD
