Metadata-Version: 2.4
Name: accelbyte-py-sdk-service-csm
Version: 0.11.0
Summary: AccelByte Python SDK - Custom Service Manager
Requires-Python: >=3.9
Requires-Dist: accelbyte-py-sdk-core
